autocompleteusers/__init__.py
autocompleteusers/autocompleteusers.py
autocompleteusers/htdocs/css/autocomplete.css
autocompleteusers/htdocs/css/autocompleteusers.css
autocompleteusers/htdocs/css/indicator.gif
autocompleteusers/htdocs/js/autocomplete.js
autocompleteusers/htdocs/js/autocomplete_perms.js
autocompleteusers/htdocs/js/autocomplete_query.js
autocompleteusers/htdocs/js/autocomplete_ticket.js
autocompleteusers/htdocs/js/autocompleteusers.js
autocompleteusers/htdocs/js/format_item.js
TracAutocompleteUsersPlugin-0.4.7.dist-info/COPYING
TracAutocompleteUsersPlugin-0.4.7.dist-info/METADATA
TracAutocompleteUsersPlugin-0.4.7.dist-info/WHEEL
TracAutocompleteUsersPlugin-0.4.7.dist-info/entry_points.txt
TracAutocompleteUsersPlugin-0.4.7.dist-info/top_level.txt
TracAutocompleteUsersPlugin-0.4.7.dist-info/RECORD
