Metadata-Version: 2.1
Name: TracAutocompleteUsersPlugin
Version: 0.4.7
Summary: complete the known trac users, AJAX style
Home-page: https://trac-hacks.org/wiki/AutocompleteUsersPlugin
Author: Jeff Hammel
Author-email: jhammel@openplans.org
Maintainer: Ryan J Ollos
Maintainer-email: ryan.j.ollos@gmail.com
License: BSD 3-Clause
Keywords: trac plugin
Platform: UNKNOWN
Classifier: Framework :: Trac
Classifier: Development Status :: 4 - Beta
Classifier: Environment :: Web Environment
Classifier: License :: OSI Approved :: Apache Software License
Classifier: Intended Audience :: Developers
Classifier: Operating System :: OS Independent
Classifier: Programming Language :: Python
Classifier: Topic :: Software Development
Requires-Dist: Trac
